foreverbull_core/__init__.py
foreverbull_core/_version.py
foreverbull_core/broker.py
foreverbull_core/cli.py
foreverbull_core/logger.py
foreverbull_core/http/__init__.py
foreverbull_core/http/backtest.py
foreverbull_core/http/exceptions.py
foreverbull_core/http/http.py
foreverbull_core/http/service.py
foreverbull_core/http/worker.py
foreverbull_core/models/__init__.py
foreverbull_core/models/backtest.py
foreverbull_core/models/base.py
foreverbull_core/models/finance.py
foreverbull_core/models/service.py
foreverbull_core/models/socket.py
foreverbull_core/models/worker.py
foreverbull_core/socket/__init__.py
foreverbull_core/socket/client.py
foreverbull_core/socket/exceptions.py
foreverbull_core/socket/nanomsg.py
foreverbull_core/socket/router.py
foreverbull_core-0.1.1.dist-info/LICENSE
foreverbull_core-0.1.1.dist-info/METADATA
foreverbull_core-0.1.1.dist-info/WHEEL
foreverbull_core-0.1.1.dist-info/top_level.txt
foreverbull_core-0.1.1.dist-info/RECORD
