Metadata-Version: 2.1
Name: foreverbull-core
Version: 0.1.1
Summary: Core Python functionality for Foreverbull
Author: Henrik Nilsson
Author-email: henrik@lhjnilsson.com
Classifier: Programming Language :: Python :: 3.8
Classifier: Programming Language :: Python :: 3.9
License-File: LICENSE
Requires-Dist: pydantic (<2.0.0,>=1.8.2)
Requires-Dist: pynng (<1.0.0,>=0.7.1)
Provides-Extra: dev
Requires-Dist: pytest (<7.0.0,>=6.2.4) ; extra == 'dev'
Requires-Dist: pytest-mock (<4.0.0,>=3.6.1) ; extra == 'dev'
Requires-Dist: requests-mock (<2.0.0,>=1.9.3) ; extra == 'dev'
Requires-Dist: flake8 (<4.0.0,>=3.9.2) ; extra == 'dev'
Requires-Dist: black (<30,>=21.7b0) ; extra == 'dev'
Requires-Dist: isort (<6.0.0,>=5.9.3) ; extra == 'dev'
Requires-Dist: pytest-cov ; extra == 'dev'
